[{"title": "Ajax and Spring MVC Controller", "score": 2.4016605615615845, "detailed_score": [0.6666666666666666, 0.3333333333333333, 0.9344403743743896], "url": "/posts/2015/Java/ajax-and-spring-mvc-controller/index.html"}, {"title": "Reading Notes for Spring 3 Core Components Tutorial Part VII (Chapter 21)", "score": 2.2969322693653593, "detailed_score": [0.6666666666666666, 0.15384615384615385, 0.9842796325683594], "url": "/posts/2014/reading-spring-3-21/index.html"}, {"title": "Reading Notes for Spring 3 Core Components Tutorial Part I (Chapter 1 to Chapter 10)", "score": 2.228613454671133, "detailed_score": [0.6666666666666666, 0.14285714285714285, 0.9460597634315491], "url": "/posts/2014/reading-spring-3-1-to-10/index.html"}, {"title": "Reading Notes for Spring 3 Core Components Tutorial Part VI (Chapter 22)", "score": 2.2191832554646025, "detailed_score": [0.6666666666666666, 0.15384615384615385, 0.9324469566345215], "url": "/posts/2014/reading-spring-3-22/index.html"}, {"title": "Reading Notes for Spring 3 Core Components Tutorial Part V (Chapter 20)", "score": 2.196205396682788, "detailed_score": [0.6666666666666666, 0.15384615384615385, 0.9171283841133118], "url": "/posts/2014/reading-spring-3-20/index.html"}, {"title": "JSTL Reference Sheet", "score": 2.165720740954081, "detailed_score": [0.6666666666666666, 0.0, 0.9993693828582764], "url": "/posts/2015/Java/jstl-reference-sheet/index.html"}, {"title": "Manning OCA Java SE 7 Reading Note: Chapter 5", "score": 2.165468434492747, "detailed_score": [0.6666666666666666, 0.0, 0.9992011785507202], "url": "/posts/2015/Java/manning-oca-java-se7-reading-note-chapter-5/index.html"}, {"title": "Use Java to Get Client's IP Address", "score": 2.165044824282328, "detailed_score": [0.6666666666666666, 0.0, 0.9989187717437744], "url": "/posts/2014/use-java-to-get-clients-ip-address/index.html"}, {"title": "Manning OCA Java SE 7 Reading Note: Chapter 2", "score": 2.151909510294596, "detailed_score": [0.6666666666666666, 0.0, 0.9901618957519531], "url": "/posts/2015/Java/manning-oca-java-se7-reading-note-chapter-2/index.html"}, {"title": "Manning OCA Java SE 7 Reading Note: Chapter 4", "score": 2.127722422281901, "detailed_score": [0.6666666666666666, 0.0, 0.9740371704101562], "url": "/posts/2015/Java/manning-oca-java-se7-reading-note-chapter-4/index.html"}]