[{"url": "/posts/2015/Front End/bootstrap3-tricks/index.html", "title": "Bootstrap3 Tips CONTINUALLY UPDATE", "detailed_score": [0.2857142857142857, 0.6666666666666666, 0.9928078651428223], "score": 2.441592750095186}, {"url": "/posts/2015/JavaScript/create-controll-dropdown/index.html", "title": "Collection of Tips for Creating/Controlling Dropdown on Web Page", "detailed_score": [0.2222222222222222, 0.18181818181818182, 0.9771366119384766], "score": 1.8697453219481188}, {"url": "/posts/2015/Java/spring-tips/index.html", "title": "Spring Tips", "detailed_score": [0.0, 0.2857142857142857, 0.9999379515647888], "score": 1.7856212130614688}, {"url": "/posts/2015/Front End/bootstrap3_sticky_footer/index.html", "title": "Bootstrap 3 Sticky Footer by Martin Bean and Ryan Fait", "detailed_score": [0.2857142857142857, 0.0, 0.9992495775222778], "score": 1.7845886519977023}, {"url": "/posts/2014/bootstrap3-api-reading-notes/index.html", "title": "Bootstrap3 API Reading Notes", "detailed_score": [0.2857142857142857, 0.0, 0.9991393089294434], "score": 1.7844232491084506}, {"url": "/posts/2015/Linux/ubuntu-tips/index.html", "title": "Ubuntu Tips", "detailed_score": [0.0, 0.2857142857142857, 0.9983174800872803], "score": 1.783190505845206}, {"url": "/posts/2015/JavaScript/javascript-tips/index.html", "title": "JavaScript Tips", "detailed_score": [0.0, 0.2857142857142857, 0.9967262744903564], "score": 1.7808036974498203}, {"url": "/posts/2015/Data Science/sql-tips/index.html", "title": "SQL Tips", "detailed_score": [0.0, 0.2857142857142857, 0.9944872856140137], "score": 1.777445214135306}, {"url": "/posts/2015/Front End/html5-tips/index.html", "title": "HTML5 Tips", "detailed_score": [0.0, 0.2857142857142857, 0.9359752535820007], "score": 1.6896771660872867}, {"url": "/posts/2015/Others/rdf-basics/index.html", "title": "RDF Basics", "detailed_score": [0.0, 0.0, 0.9999983906745911], "score": 1.4999975860118866}]