[{"url": "/posts/2015/Data Science/use-amazon-ec2-to-host-ipython-notebook/index.html", "detailed_score": [0.3333333333333333, 0.2857142857142857, 0.9996770620346069], "title": "Use Amazon EC2 to Host IPython Notebook", "score": 2.1185632120995295}, {"url": "/posts/2015/Data Science/sparksql-basics/index.html", "detailed_score": [0.5714285714285714, 0.0, 0.9874545335769653], "title": "SparkSQL Basics", "score": 2.052610371794019}, {"url": "/posts/2015/Data Science/how-to-build-a-basic-nikola-blog-and-deloy-to-github-page/index.html", "detailed_score": [0.2857142857142857, 0.0, 0.9873941540718079], "title": "How to Build A Basic Nikola Blog and Deploy to Github Page", "score": 1.7668055168219974}, {"url": "/posts/2015/Data Science/search-engine-basics-lucene/index.html", "detailed_score": [0.25, 0.0, 0.9996337294578552], "title": "Search Engine Basics (Including Lucene)", "score": 1.7494505941867828}, {"url": "/posts/2015/Linux/ubuntu-tips/index.html", "detailed_score": [0.0, 0.2, 0.9909340143203735], "title": "Ubuntu Tips", "score": 1.6864010214805603}, {"url": "/posts/2014/install-ubuntu-on-windows-8-machine/index.html", "detailed_score": [0.0, 0.2222222222222222, 0.9759123921394348], "title": "Install Ubuntu 14 on External Drive from Windows8 Machine with Node.js, Hexo and Jekyll", "score": 1.6860908104313745}, {"url": "/posts/2015/Java/apache-velocity-basics/index.html", "detailed_score": [0.0, 0.16666666666666666, 0.9976730942726135], "title": "Apache Velocity Language Basics", "score": 1.663176308075587}, {"url": "/posts/2018/consulting/reading-note-for-the-mckinsey-way/index.html", "detailed_score": [0.0, 0.0, 0.9999444484710693], "title": "Reading Notes for \"The McKinsey Mind\" written by Ethan M. Rasiel and Paul N. Friga", "score": 1.499916672706604}, {"url": "/posts/2015/Algorithm Data Structure/algorithm-and-data-structure-basics-linkedlist/index.html", "detailed_score": [0.0, 0.0, 0.9998155236244202], "title": "Algorithm and Data Structure Basics - Linked List", "score": 1.4997232854366302}, {"url": "/posts/2015/Algorithm Data Structure/algorithm-and-data-structure-basics-dynamic-programming/index.html", "detailed_score": [0.0, 0.0, 0.9996766448020935], "title": "Algorithm and Data Structure Basics - Dynamic Programming", "score": 1.4995149672031403}]