[{"title": "HTML5 Tips", "score": 2.292306977510452, "url": "/posts/2015/Front End/html5-tips/index.html", "detailed_score": [0.8, 0.0, 0.9948713183403015]}, {"title": "JavaScript and Color", "score": 2.166642705599467, "url": "/posts/2015/JavaScript/javascript-color/index.html", "detailed_score": [0.6666666666666666, 0.0, 0.9999840259552002]}, {"title": "Number Precision in JavaScript", "score": 2.166589597860972, "url": "/posts/2015/JavaScript/number-precision-in-javascript/index.html", "detailed_score": [0.6666666666666666, 0.0, 0.9999486207962036]}, {"title": "Boostrap3 Date Picker", "score": 2.166243145863215, "url": "/posts/2015/JavaScript/bootstrap3-date-picker/index.html", "detailed_score": [0.6666666666666666, 0.0, 0.999717652797699]}, {"title": "Regular Expression", "score": 2.1643012265364328, "url": "/posts/2015/Web Development Tips/regular-expression/index.html", "detailed_score": [0.6666666666666666, 0.0, 0.9984230399131775]}, {"title": "Window.Location Property", "score": 2.159925470749537, "url": "/posts/2015/JavaScript/window-location-property/index.html", "detailed_score": [0.6666666666666666, 0.0, 0.9955058693885803]}, {"title": "Bootstrap 3 Sticky Footer by Martin Bean and Ryan Fait", "score": 2.1009598771731057, "url": "/posts/2015/Front End/bootstrap3_sticky_footer/index.html", "detailed_score": [0.6666666666666666, 0.0, 0.9561954736709595]}, {"title": "Reading Note - JavaScript Scoping, Hoisting and Others", "score": 2.075939337412516, "url": "/posts/2016/JavaScript/reading-note-javascript-scoping-hoisting-and-others/index.html", "detailed_score": [0.6666666666666666, 0.0, 0.9395151138305664]}, {"title": "AngularJS Basics", "score": 1.9999154210090637, "url": "/posts/2015/JavaScript/angularjs-basics/index.html", "detailed_score": [0.5, 0.0, 0.9999436140060425]}, {"title": "Reading Notes for D3.js Part I (Chapter 1 to Chapter 5)", "score": 1.9988803565502167, "url": "/posts/2014/reading-d3-1-to-5/index.html", "detailed_score": [0.5, 0.0, 0.9992535710334778]}]