[{"url": "/posts/2018/finance/cfa-reading-notes-1/index.html", "detailed_score": [1.0, 0.17391304347826086, 0.9741736650466919], "title": "Reading Notes for CFA1 Program Curriculum Volume 1 - QUANTITATIVE METHODS part", "score": 2.6351735410482986}, {"url": "/posts/2018/business/reading-map-for-say-it-with-chartspresentations/index.html", "detailed_score": [0.6666666666666666, 0.1111111111111111, 0.9934074282646179], "title": "Reading Map for Say It With Charts & Presentations", "score": 2.2678889201747046}, {"url": "/posts/2018/business/reading-notes-for-excel-hanshu-hen-jian-dan/index.html", "detailed_score": [0.6666666666666666, 0.2, 0.8902272582054138], "title": "(In Process)Reading Notes for \"\u522b\u6015, Excel\u51fd\u6570\u5176\u5b9e\u5f88\u7b80\u5355I\" Written by Excel Home", "score": 2.2020075539747874}, {"url": "/posts/2018/book/highlights-for-fully-engaged/index.html", "detailed_score": [0.5, 0.16, 0.9636797308921814], "title": "(Chinese) Highlights for Fully Engaged! Using the Practicing Mind in Daily Life written by Thomas M. Sterner", "score": 2.1055195963382722}, {"url": "/posts/2017/front-end/professional-javascript-oop/index.html", "detailed_score": [0.6666666666666666, 0.0, 0.9137294888496399], "title": "Object Oriented Programming in Professional JavaScript for Web Developers", "score": 2.0372608999411264}, {"url": "/posts/2017/book/chinese-zi-kong-li-highlight/index.html", "detailed_score": [0.5, 0.0, 0.9986363053321838], "title": "(In Chinese) \u81ea\u63a7\u529b\u9605\u8bfb\u6458\u6284 (Kindle \u5bfc\u51fa)", "score": 1.9979544579982758}, {"url": "/posts/2017/book/chinese-the-element-of-style-reading-note/index.html", "detailed_score": [0.4, 0.09523809523809523, 0.9884679317474365], "title": "(In Chinese) \u98ce\u683c\u7684\u8981\u7d20-\u9605\u8bfb\u6458\u6284 (The Elements of Style - Reading Note)", "score": 1.97793999285925}, {"url": "/posts/2018/book/highlights-for-jingzhunmuli/index.html", "detailed_score": [0.5, 0.1111111111111111, 0.885064959526062], "title": "(Chinese) Highlights for \u79c1\u306f\u3044\u304f\u3089?(\u7cbe\u51c6\u52aa\u529b) written by Mahito Noguchi(\u91ce\u53e3\u771f\u4eba)", "score": 1.9387085504002042}, {"url": "/posts/2017/book/chinese-poor-charlies-almanack-1/index.html", "detailed_score": [0.4, 0.0, 0.9931424260139465], "title": "(In Chinese) \u7a77\u67e5\u7406\u5b9d\u5178-\u9605\u8bfb\u6458\u62841 \uff08\u4f01\u4e1a\u4e0e\u6295\u8d44\uff09", "score": 1.8897136390209197}, {"url": "/posts/2018/consulting/chapter-2-of-case-in-point-graph-analysis/index.html", "detailed_score": [1.0, 0.07692307692307693, 0.5376925468444824], "title": "Chapter 2 of Case in Point: Graph Analysis for Consulting and Case Interviews, written by Marc P. Cosentino Mukund Jain", "score": 1.8834618971898005}]