[{"title": "Reading Notes for Spring 3 Core Components Tutorial Part I (Chapter 1 to Chapter 10)", "score": 3.264833468198776, "url": "/posts/2014/reading-spring-3-1-to-10/index.html", "detailed_score": [1.0, 0.8, 0.9765556454658508]}, {"title": "Reading Notes for Spring 3 Core Components Tutorial Part VII (Chapter 21)", "score": 3.2468232810497284, "url": "/posts/2014/reading-spring-3-21/index.html", "detailed_score": [1.0, 0.75, 0.9978821873664856]}, {"title": "Reading Notes for Spring 3 Core Components Tutorial Part VI (Chapter 22)", "score": 3.201076328754425, "url": "/posts/2014/reading-spring-3-22/index.html", "detailed_score": [1.0, 0.75, 0.9673842191696167]}, {"title": "Reading Notes for Spring 3 Core Components Tutorial Part V (Chapter 20)", "score": 3.1844001412391663, "url": "/posts/2014/reading-spring-3-20/index.html", "detailed_score": [1.0, 0.75, 0.9562667608261108]}, {"title": "Reading Notes for Spring 3 Core Components Tutorial Part Part III (Chapter 14 to Chapter 16)", "score": 3.134623573376582, "url": "/posts/2014/reading-spring-3-14-to-16/index.html", "detailed_score": [1.0, 0.7692307692307693, 0.910261869430542]}, {"title": "Reading Notes for Spring 3 Core Components Tutorial Part I Part IV (Chapter 17 to Chapter 19)", "score": 3.059392974926875, "url": "/posts/2014/reading-spring-3-17-to-19/index.html", "detailed_score": [1.0, 0.7692307692307693, 0.8601081371307373]}, {"title": "Manning OCA Java SE 7 Reading Note: Chapter 3", "score": 2.7322845675728535, "url": "/posts/2015/Java/manning-oca-java-se7-reading-note-chapter-3/index.html", "detailed_score": [1.0, 0.2727272727272727, 0.9730381965637207]}, {"title": "Manning OCA Java SE 7 Reading Note: Chapter 4", "score": 2.671762937849218, "url": "/posts/2015/Java/manning-oca-java-se7-reading-note-chapter-4/index.html", "detailed_score": [1.0, 0.18181818181818182, 0.9932965040206909]}, {"title": "Manning OCA Java SE 7 Reading Note: Chapter 7", "score": 2.670572769074213, "url": "/posts/2015/Java/manning-oca-java-se7-reading-note-chapter-7/index.html", "detailed_score": [1.0, 0.19047619047619047, 0.9867310523986816]}, {"title": "Manning OCA Java SE 7 Reading Note: Chapter 5", "score": 2.6643616502935235, "url": "/posts/2015/Java/manning-oca-java-se7-reading-note-chapter-5/index.html", "detailed_score": [1.0, 0.18181818181818182, 0.9883623123168945]}]